turbomind/__init__.py
turbomind/linear.py
turbomind/utils.py
turbomind/version.py
turbomind/lib/_turbomind_ext.cpython-38-x86_64-linux-gnu.so
turbomind-0.0.2.dist-info/LICENSE
turbomind-0.0.2.dist-info/METADATA
turbomind-0.0.2.dist-info/WHEEL
turbomind-0.0.2.dist-info/top_level.txt
turbomind-0.0.2.dist-info/RECORD
