Metadata-Version: 2.1
Name: turbomind
Version: 0.0.2
Summary: CUDA kernels used for LLM Quantization
Author: OpenMMLab
Author-email: openmmlab@gmail.com
Classifier: Programming Language :: Python :: 3.8
Classifier: Programming Language :: Python :: 3.9
Classifier: Programming Language :: Python :: 3.10
Classifier: Programming Language :: Python :: 3.11
Classifier: Programming Language :: Python :: 3.12
Classifier: Intended Audience :: Developers
Classifier: Intended Audience :: Education
Classifier: Intended Audience :: Science/Research
License-File: LICENSE
Requires-Dist: torch
Provides-Extra: all
Requires-Dist: pybind11<=2.13.1; extra == "all"
Requires-Dist: setuptools; extra == "all"
Requires-Dist: torch; extra == "all"
